{
  "tour": "atp",
  "player_id": 100359,
  "full_name": "Richard Lewis",
  "ioc": "GBR",
  "slams": [
    "Australian Open",
    "Roland Garros",
    "Wimbledon",
    "US Open"
  ],
  "results": {
    "1973": {
      "Wimbledon": "1R"
    },
    "1974": {
      "Australian Open": "2R"
    },
    "1975": {
      "Wimbledon": "1R",
      "Australian Open": "3R"
    },
    "1976": {
      "Wimbledon": "3R",
      "Roland Garros": "1R"
    },
    "1977": {
      "Australian Open": "4R",
      "Roland Garros": "1R",
      "Wimbledon": "1R",
      "US Open": "1R"
    },
    "1978": {
      "Roland Garros": "1R",
      "Wimbledon": "1R",
      "Australian Open": "2R"
    },
    "1979": {
      "Wimbledon": "1R"
    },
    "1980": {
      "Wimbledon": "1R"
    },
    "1981": {
      "Wimbledon": "1R",
      "Australian Open": "3R"
    },
    "1982": {
      "Wimbledon": "1R",
      "Australian Open": "2R"
    },
    "1983": {
      "Wimbledon": "1R"
    },
    "1984": {
      "Wimbledon": "1R"
    }
  }
}