{
  "tour": "wta",
  "player_id": 200089,
  "full_name": "Miriam Oremans",
  "ioc": "NED",
  "slams": [
    "Australian Open",
    "Roland Garros",
    "Wimbledon",
    "US Open"
  ],
  "results": {
    "1990": {
      "US Open": "2R"
    },
    "1991": {
      "Australian Open": "1R",
      "Wimbledon": "1R"
    },
    "1992": {
      "Wimbledon": "1R"
    },
    "1993": {
      "Australian Open": "3R",
      "Roland Garros": "2R",
      "Wimbledon": "4R",
      "US Open": "1R"
    },
    "1994": {
      "Roland Garros": "3R",
      "Australian Open": "1R",
      "Wimbledon": "1R",
      "US Open": "1R"
    },
    "1995": {
      "Wimbledon": "3R",
      "Australian Open": "2R",
      "Roland Garros": "2R",
      "US Open": "1R"
    },
    "1996": {
      "Wimbledon": "2R",
      "Australian Open": "1R",
      "Roland Garros": "3R",
      "US Open": "2R"
    },
    "1997": {
      "Australian Open": "1R",
      "Roland Garros": "1R",
      "Wimbledon": "1R",
      "US Open": "3R"
    },
    "1998": {
      "Wimbledon": "4R",
      "Australian Open": "2R",
      "Roland Garros": "2R",
      "US Open": "1R"
    },
    "1999": {
      "Australian Open": "1R",
      "Roland Garros": "1R",
      "Wimbledon": "1R",
      "US Open": "1R"
    },
    "2000": {
      "Wimbledon": "3R",
      "Australian Open": "3R",
      "Roland Garros": "2R",
      "US Open": "2R"
    },
    "2001": {
      "Australian Open": "2R",
      "Roland Garros": "1R",
      "Wimbledon": "1R",
      "US Open": "2R"
    },
    "2002": {
      "Wimbledon": "3R",
      "Australian Open": "1R",
      "Roland Garros": "1R",
      "US Open": "1R"
    }
  }
}