{
  "tour": "wta",
  "player_id": 200845,
  "full_name": "Patricia Walkden",
  "ioc": "RSA",
  "slams": [
    "Australian Open",
    "Roland Garros",
    "Wimbledon",
    "US Open"
  ],
  "results": {
    "1968": {
      "Wimbledon": "3R",
      "Roland Garros": "4R"
    },
    "1969": {
      "Wimbledon": "4R",
      "Roland Garros": "4R"
    },
    "1970": {
      "Roland Garros": "3R",
      "Wimbledon": "1R",
      "US Open": "4R"
    },
    "1972": {
      "Wimbledon": "3R",
      "US Open": "1R",
      "Roland Garros": "3R"
    },
    "1973": {
      "Roland Garros": "4R",
      "Wimbledon": "3R",
      "US Open": "2R"
    }
  }
}