{
  "tour": "wta",
  "player_id": 201022,
  "full_name": "Debbie Spence Nasim",
  "ioc": "USA",
  "slams": [
    "Australian Open",
    "Roland Garros",
    "Wimbledon",
    "US Open"
  ],
  "results": {
    "1984": {
      "US Open": "2R"
    },
    "1985": {
      "Roland Garros": "4R",
      "US Open": "1R"
    },
    "1986": {
      "Roland Garros": "1R",
      "Wimbledon": "1R",
      "US Open": "1R"
    },
    "1987": {
      "Roland Garros": "1R",
      "Wimbledon": "1R",
      "US Open": "1R"
    }
  }
}